mitsubishi_connect_client/__init__.py
mitsubishi_connect_client/mitsubishi_connect_client.py
mitsubishi_connect_client/remote_operation_response.py
mitsubishi_connect_client/token_state.py
mitsubishi_connect_client/vehicle.py
mitsubishi_connect_client/vehicle_state.py
mitsubishi_connect_client/vehicle_status.py
mitsubishi_connect_client-0.0.7.dist-info/licenses/LICENSE
tests/__init__.py
tests/test__init__.py
tests/test_live.py
tests/test_mitsubishi_connect_client.py
tests/test_remote_operaton_response.py
tests/test_vehicle.py
tests/test_vehicle_state.py
tests/test_vehicle_status.py
mitsubishi_connect_client-0.0.7.dist-info/METADATA
mitsubishi_connect_client-0.0.7.dist-info/WHEEL
mitsubishi_connect_client-0.0.7.dist-info/top_level.txt
mitsubishi_connect_client-0.0.7.dist-info/RECORD
