Metadata-Version: 2.4
Name: mitsubishi_connect_client
Version: 0.0.7
Summary: Client for the Mitsubishi Connect API
Home-page: https://github.com/pcartwright81/mitsubishi_connect_client
Author: Patrick Cartwright
Author-email: pcartwright1981@gmail.com
Classifier: Programming Language :: Python :: 3
Classifier: License :: OSI Approved :: MIT License
Classifier: Operating System :: OS Independent
License-File: LICENSE
Dynamic: author
Dynamic: author-email
Dynamic: classifier
Dynamic: description
Dynamic: description-content-type
Dynamic: home-page
Dynamic: license-file
Dynamic: summary
